[{"_id":{"$oid":"5fdc8d487a8fe2336c81e25c"},"sourceId":"5fdc8b297a8fe2336c81e258","name":"N - Source","status":1,"__v":0},{"_id":{"$oid":"5fdc8d687a8fe2336c81e25d"},"sourceId":"5fdc8b297a8fe2336c81e258","name":"P - Source","status":1,"__v":0},{"_id":{"$oid":"5fdc8d777a8fe2336c81e25e"},"sourceId":"5fdc8b297a8fe2336c81e258","name":"K - Source","status":1,"__v":0},{"_id":{"$oid":"5fdc8dd97a8fe2336c81e25f"},"sourceId":"5fdc8b387a8fe2336c81e259","name":"NPK 15-15-15","status":1,"__v":0},{"_id":{"$oid":"5fdc8ded7a8fe2336c81e260"},"sourceId":"5fdc8b387a8fe2336c81e259","name":"NPK 20-20-20","status":1,"__v":0},{"_id":{"$oid":"5fdc8e247a8fe2336c81e261"},"sourceId":"5fdc8b4b7a8fe2336c81e25a","name":"N - Source","status":1,"__v":0},{"_id":{"$oid":"5fdc8e527a8fe2336c81e262"},"sourceId":"5fdc8b4b7a8fe2336c81e25a","name":"K - Source","status":1,"__v":0},{"_id":{"$oid":"5fdc8e757a8fe2336c81e263"},"sourceId":"5fdc8b297a8fe2336c81e258","name":"S - Source","status":1,"__v":0},{"_id":{"$oid":"5fdc8eb37a8fe2336c81e264"},"sourceId":"5fdc8b4b7a8fe2336c81e25a","name":"S - Source","status":1,"__v":0},{"_id":{"$oid":"5fdc8ee27a8fe2336c81e265"},"sourceId":"5fdc8b5a7a8fe2336c81e25b","name":"N - Source","status":1,"__v":0},{"_id":{"$oid":"5fdc8f3ba9d0063ca8af9c31"},"sourceId":"5fdc8b5a7a8fe2336c81e25b","name":"S - Source","status":1,"__v":0},{"_id":{"$oid":"5fdc8f4ea9d0063ca8af9c32"},"sourceId":"5fdc8b5a7a8fe2336c81e25b","name":"P - Source","status":1,"__v":0},{"_id":{"$oid":"5fdc90f2a29e4a28287cb94f"},"sourceId":"5fdc8b5a7a8fe2336c81e25b","name":"K - Source","status":1,"__v":0}]
